qt_material_icons/__init__.py
qt_material_icons/_icon.py
qt_material_icons/resources/icons_outlined_20.py
qt_material_icons/resources/icons_outlined_24.py
qt_material_icons/resources/icons_outlined_40.py
qt_material_icons/resources/icons_outlined_48.py
qt_material_icons/resources/icons_rounded_20.py
qt_material_icons/resources/icons_rounded_24.py
qt_material_icons/resources/icons_rounded_40.py
qt_material_icons/resources/icons_rounded_48.py
qt_material_icons/resources/icons_sharp_20.py
qt_material_icons/resources/icons_sharp_24.py
qt_material_icons/resources/icons_sharp_40.py
qt_material_icons/resources/icons_sharp_48.py
qt_material_icons-0.3.1.dist-info/licenses/LICENSE
qt_material_icons-0.3.1.dist-info/METADATA
qt_material_icons-0.3.1.dist-info/WHEEL
qt_material_icons-0.3.1.dist-info/top_level.txt
qt_material_icons-0.3.1.dist-info/RECORD
