Metadata-Version: 2.4
Name: qt-material-icons
Version: 0.3.1
Summary: Material Symbols by Google for Qt using PySide
Author: Beat Reichenbach
License: MIT
Requires-Python: >=3.6
License-File: LICENSE
Provides-Extra: dev
Requires-Dist: black>=24.0; extra == "dev"
Requires-Dist: python-semantic-release>=9.0; extra == "dev"
Requires-Dist: PySide6; extra == "dev"
Requires-Dist: qt_themes>=0.2; extra == "dev"
Provides-Extra: pyside2
Requires-Dist: PySide2; extra == "pyside2"
Provides-Extra: pyside6
Requires-Dist: PySide6; extra == "pyside6"
Provides-Extra: qtpy
Requires-Dist: qtpy<3,>=2.0; extra == "qtpy"
Dynamic: license-file
